kudo/__init__.py
kudo_ui-0.0.1.dist-info/METADATA
kudo_ui-0.0.1.dist-info/WHEEL
kudo_ui-0.0.1.dist-info/top_level.txt
kudo_ui-0.0.1.dist-info/RECORD
