Metadata-Version: 2.4
Name: kudo-ui
Version: 0.0.1
Summary: Experimental Python visualization toolkit (early placeholder)
Author: Manas Maheshwari
License: MIT
Requires-Python: >=3.8
